mattermost_api/__init__.py
mattermost_api/mattermost_api.py
tests/__init__.py
tests/integration/__init__.py
tests/integration/test_integration_mattermost_api.py
tests/unit/__init__.py
tests/unit/test_mattermost_api.py
mattermost_py_api-1.0.5.dist-info/LICENSE
mattermost_py_api-1.0.5.dist-info/METADATA
mattermost_py_api-1.0.5.dist-info/WHEEL
mattermost_py_api-1.0.5.dist-info/top_level.txt
mattermost_py_api-1.0.5.dist-info/RECORD
