Metadata-Version: 2.1
Name: mattermost_py_api
Version: 1.0.5
Summary: A simple Python library for making Mattermost API calls
Home-page: https://github.com/jlandells/mm-py-api
Author: John Landells
Author-email: john.landells@mattermost.com
License: MIT
Classifier: Programming Language :: Python :: 3
Classifier: License :: OSI Approved :: MIT License
Classifier: Operating System :: OS Independent
Requires-Python: >=3.6
License-File: LICENSE
Requires-Dist: requests
